{
  "dataset_info": {
    "seed": 107,
    "dataset_index": 6,
    "node_count": 20,
    "edge_count": 20,
    "graph_type": "ER",
    "shifted_nodes": [
      8,
      12,
      14,
      10
    ],
    "shift_types": {
      "8": "noise_skew",
      "12": "noise_skew",
      "14": "noise_skew",
      "10": "noise_skew"
    },
    "shift_case": "noise_skew_noise_skew"
  },
  "model": "gpr",
  "estimated_shift_types": {
    "8": "noise",
    "10": "noise",
    "12": "function",
    "14": "noise"
  }
}