{
  "dataset_info": {
    "seed": 118,
    "dataset_index": 17,
    "node_count": 20,
    "edge_count": 20,
    "graph_type": "ER",
    "shifted_nodes": [
      15,
      14,
      13,
      12
    ],
    "shift_types": {
      "15": "noise_std",
      "14": "noise_std",
      "13": "noise_std",
      "12": "noise_std"
    },
    "shift_case": "noise_std_noise_std"
  },
  "detected_shifts": [
    5,
    10,
    11,
    12,
    13,
    14,
    18
  ],
  "shifted_nodes": [
    15,
    14,
    13,
    12
  ]
}